CONGA/__init__.py
CONGA/__main__.py
CONGA/version.py
CONGA/tests/__init__.py
CONGA/tests/unit_test.py
CONGA/utils/CONGA_functions.py
CONGA/utils/__init__.py
CONGA/utils/peptides.py
CONGA-3.0.7.dist-info/LICENSE
CONGA-3.0.7.dist-info/METADATA
CONGA-3.0.7.dist-info/WHEEL
CONGA-3.0.7.dist-info/top_level.txt
CONGA-3.0.7.dist-info/RECORD
