Metadata-Version: 2.1
Name: CONGA
Version: 3.0.7
Summary: Combined Open and Narrow searches via Group Analysis
Home-page: https://github.com/freejstone/CONGA
Author: Jack Freestone
Author-email: jfre0619@uni.sydney.edu.au
Classifier: Programming Language :: Python :: 3
Classifier: License :: OSI Approved :: MIT License
Classifier: Operating System :: OS Independent
Requires-Python: >=3.9.0, <=3.10.13
License-File: LICENSE
Requires-Dist: pyteomics
Requires-Dist: pandas
Requires-Dist: numpy
Requires-Dist: scipy
Requires-Dist: tdqm
Requires-Dist: matplotlib
Requires-Dist: pyascore
